djangopollapp/__init__.py
djangopollapp/admin.py
djangopollapp/apps.py
djangopollapp/middleware.py
djangopollapp/models.py
djangopollapp/tests.py
djangopollapp/views.py
djangopollapp/api/__init__.py
djangopollapp/api/urls.py
djangopollapp/api/v1/__init__.py
djangopollapp/api/v1/serializers.py
djangopollapp/api/v1/urls.py
djangopollapp/api/v1/views.py
djangopollapp/migrations/0001_initial.py
djangopollapp/migrations/__init__.py
djangopollapp-0.1.1.dist-info/LICENSE
djangopollapp-0.1.1.dist-info/METADATA
djangopollapp-0.1.1.dist-info/WHEEL
djangopollapp-0.1.1.dist-info/top_level.txt
djangopollapp-0.1.1.dist-info/RECORD
