Metadata-Version: 2.1
Name: djangopollapp
Version: 0.1.1
Summary: A simple polls application
Home-page: https://github.com/c0derbug/djangopollapp.git
Author: Coder Bug
Author-email: thecoderbug@gmail.com
License: UNKNOWN
Platform: UNKNOWN
Classifier: Programming Language :: Python :: 3
Classifier: License :: OSI Approved :: MIT License
Classifier: Operating System :: OS Independent
Requires-Python: >=3.5.2
